gpr_algorithm/__init__.py
gpr_algorithm/algorithm.py
gpr_algorithm-1.0.0.dist-info/WHEEL
gpr_algorithm-1.0.0.dist-info/METADATA
gpr_algorithm-1.0.0.dist-info/RECORD
