Metadata-Version: 2.1
Name: gpr-algorithm
Version: 1.0.0
Summary: Gene Programming Rules (GPR) implementation
Author: Anna Czmil
Author-email: czmilanna@gmail.com
Requires-Python: >=3.8,<3.11
Classifier: Programming Language :: Python :: 3
Classifier: Programming Language :: Python :: 3.10
Classifier: Programming Language :: Python :: 3.8
Classifier: Programming Language :: Python :: 3.9
Requires-Dist: deap (==1.3.1)
Requires-Dist: geppy (==0.1.3)
Requires-Dist: numpy (==1.21.6)
Requires-Dist: scikit-learn (==1.0.2)
Requires-Dist: sympy (==1.9)
